subarashii/__init__.py
subarashii/db.py
subarashii/exception/attribute_not_found_exception.py
subarashii/exception/entity_not_found_exception.py
subarashii/model/subarashii_table.py
subarashii/repository/__init__.py
subarashii/repository/crud_repository.py
subarashii/repository/repository.py
subarashii/test/__init__.py
subarashii/test/conftest.py
subarashii/test/test_crud_repository/test_crud_repository_count.py
subarashii/test/test_crud_repository/test_crud_repository_delete.py
subarashii/test/test_crud_repository/test_crud_repository_delete_all.py
subarashii/test/test_crud_repository/test_crud_repository_exists_by_id.py
subarashii/test/test_crud_repository/test_crud_repository_get_all.py
subarashii/test/test_crud_repository/test_crud_repository_get_by.py
subarashii/test/test_crud_repository/test_crud_repository_get_by_id.py
subarashii/test/test_crud_repository/test_crud_repository_save.py
subarashii/test/test_crud_repository/test_crud_repository_save_all.py
subarashii/test/test_crud_repository/test_crud_repository_update.py
subarashii-1.1.2.dist-info/licenses/LICENSE
subarashii-1.1.2.dist-info/METADATA
subarashii-1.1.2.dist-info/WHEEL
subarashii-1.1.2.dist-info/top_level.txt
subarashii-1.1.2.dist-info/RECORD
