Metadata-Version: 2.4
Name: subarashii
Version: 1.1.2
Summary: Reusable Python base classes for effortless CRUD repositories.
Author-email: Lucas Fernandes <hzokbe@gmail.com>
License: MIT
Requires-Python: >=3.12
License-File: LICENSE
Requires-Dist: psycopg2-binary>=2.9.11
Requires-Dist: python-dotenv>=1.2.1
Requires-Dist: sqlalchemy>=2.0.46
Dynamic: license-file
